{
  "alias": "madwhips_british",
  "username": "British Exotic Hyper Supercars",
  "descriptionProfile": [
    "Anthony@MadWhips.com 👻 SnapChat: MadWhips Learn How I Make $250,000+ posting photos! 👇👇👇👇👇👇👇👇👇👇",
    "Anthony@MadWhips.com 👻 SnapChat: MadWhips Learn How I Make $250,000+ posting photos! 👇👇👇👇👇👇👇👇👇👇"
  ],
  "urlProfile": "https://www.instagram.com/madwhips_british/",
  "urlImgProfile": "https://scontent.cdninstagram.com/t51.2885-19/s320x320/11373970_1674446906134236_195878709_a.jpg",
  "website": "www.WolfMillionaire.com",
  "numberPosts": 3073,
  "numberFollowers": 348229,
  "numberFollowing": 31,
  "private": false,
  "posts": [
    {
      "url": "https://www.instagram.com/p/BTiKiLKhyeY/?taken-by=madwhips_british",
      "urlImage": "https://scontent-lga3-1.cdninstagram.com/vp/f04abfe684842060f821ac568d5be437/5C932F06/t51.2885-15/sh0.08/e35/s640x640/28765158_340079733178224_5183760475250229248_n.jpg",
      "isVideo": false,
      "multipleImage": false,
      "tags": [
        "#WolfMillionaire",
        "#Bentley",
        "#Continental",
        "#BentleyContinental",
        "#MadWhips"
      ],
      "mentions": [
        "@wolf_millionaire",
        "@wolf_millionaire",
        "@wolf_millionaire",
        "@k",
        "@k.ignorance",
        "@wolf_millionaire"
      ],
      "description": "Bentley Continental GT II\nCheck Out 💰 @wolf_millionaire 💰for our GUIDES To GROW Followers & Make MONEY @wolf_millionaire\n\nCLICK LINK IN BIO 🔥\n\nFREE GUIDE-> 🚨 www.WolfMillionaire.com 🚨\n\nCheck Out @wolf_millionaire \n#WolfMillionaire\nPhoto by @k.ignorance\n#Bentley #Continental #BentleyContinental #MadWhips",
      "localization": null,
      "date": "2017-04-30T05:00:00.000Z",
      "numberLikes": 576,
      "filename": "18251982_1315438475214836_6047730530235973632_n.jpg"
    },
    {
      "url": "https://www.instagram.com/p/BTh8No7BDKt/?taken-by=madwhips_british",
      "urlImage": "https://scontent-lga3-1.cdninstagram.com/vp/70930ffa155278eb4b126b2e9ae5c700/5C93991B/t51.2885-15/sh0.08/e35/s640x640/28766608_1909888559324009_2076585166851014656_n.jpg",
      "isVideo": false,
      "multipleImage": false,
      "tags": [
        "#WolfMillionaire",
        "#AstonMartin",
        "#Vanquish",
        "#AstonMartinVanquish",
        "#MadWhips"
      ],
      "mentions": [
        "@wolf_millionaire",
        "@wolf_millionaire",
        "@wolf_millionaire",
        "@upscale_exotics",
        "@upscale_exotics",
        "@wolf_millionaire"
      ],
      "description": "Aston Martin Vanquish\nCheck Out 💰 @wolf_millionaire 💰for our GUIDES To GROW Followers & Make MONEY @wolf_millionaire\n\nCLICK LINK IN BIO 🔥\n\nFREE GUIDE-> 🚨 www.WolfMillionaire.com 🚨\n\nCheck Out @wolf_millionaire \n#WolfMillionaire\nPhoto by @upscale_exotics \n#AstonMartin #Vanquish #AstonMartinVanquish #MadWhips",
      "localization": null,
      "date": "2017-04-30T05:00:00.000Z",
      "numberLikes": 797,
      "filename": "18161210_389459494780926_6173589830971162624_n.jpg"
    },
    {
      "url": "https://www.instagram.com/p/BTfkDbABvQl/?taken-by=madwhips_british",
      "urlImage": "https://scontent-lga3-1.cdninstagram.com/vp/b54e0a43a2be56b94fc9d9ad5e0e9ffb/5C784A07/t51.2885-15/sh0.08/e35/s640x640/28753046_645187432318224_8678682523439464448_n.jpg",
      "isVideo": false,
      "multipleImage": false,
      "tags": [
        "#WolfMillionaire",
        "#RollsRoyce",
        "#Wraith",
        "#RollsRoyceWraith",
        "#MadWhips"
      ],
      "mentions": [
        "@wolf_millionaire",
        "@wolf_millionaire",
        "@wolf_millionaire",
        "@carspotting_mike",
        "@carspotting_mike",
        "@wolf_millionaire"
      ],
      "description": "Rolls Royce Wraith \nCheck Out 💰 @wolf_millionaire 💰for our GUIDES To GROW Followers & Make MONEY @wolf_millionaire\n\nCLICK LINK IN BIO 🔥\n\nFREE GUIDE-> 🚨 www.WolfMillionaire.com 🚨\n\nCheck Out @wolf_millionaire \n#WolfMillionaire\nPhoto by @carspotting_mike \n#RollsRoyce #Wraith #RollsRoyceWraith #MadWhips",
      "localization": null,
      "date": "2017-04-29T05:00:00.000Z",
      "numberLikes": 2606,
      "filename": "18161335_131418740736173_3238194466879700992_n.jpg"
    },
    {
      "url": "https://www.instagram.com/p/BTfWoK2BgU2/?taken-by=madwhips_british",
      "urlImage": "https://scontent-lga3-1.cdninstagram.com/vp/0fb3c8a494d47c7fabafa02727f7de27/5C8FB571/t51.2885-15/sh0.08/e35/s640x640/28754334_111545256320470_5764149267203620864_n.jpg",
      "isVideo": false,
      "multipleImage": false,
      "tags": [
        "#WolfMillionaire",
        "#Lotus",
        "#Exige",
        "#LotusExige",
        "#MadWhips"
      ],
      "mentions": [
        "@wolf_millionaire",
        "@wolf_millionaire",
        "@wolf_millionaire",
        "@arooc",
        "@arooc.photo",
        "@wolf_millionaire"
      ],
      "description": "Lotus Exige \nCheck Out 💰 @wolf_millionaire 💰for our GUIDES To GROW Followers & Make MONEY @wolf_millionaire\n\nCLICK LINK IN BIO 🔥\n\nFREE GUIDE-> 🚨 www.WolfMillionaire.com 🚨\n\nCheck Out @wolf_millionaire \n#WolfMillionaire\nPhoto by @arooc.photo\n#Lotus #Exige #LotusExige #MadWhips",
      "localization": null,
      "date": "2017-04-29T05:00:00.000Z",
      "numberLikes": 1941,
      "filename": "18096651_154013605132507_7334753631222104064_n.jpg"
    },
    {
      "url": "https://www.instagram.com/p/BTc9IY0BHrC/?taken-by=madwhips_british",
      "urlImage": "https://scontent-lga3-1.cdninstagram.com/vp/3c26e36569393392279a366010204751/5C92F3EC/t51.2885-15/sh0.08/e35/s640x640/29093738_421615151609618_4571061413128175616_n.jpg",
      "isVideo": false,
      "multipleImage": false,
      "tags": [
        "#WolfMillionaire",
        "#AstonMartin",
        "#DB11",
        "#AstonMartinDB11",
        "#MadWhips"
      ],
      "mentions": [
        "@wolf_millionaire",
        "@wolf_millionaire",
        "@wolf_millionaire",
        "@zerotosixtylifestyle",
        "@zerotosixtylifestyle",
        "@wolf_millionaire"
      ],
      "description": "Aston Martin DB11 \nCheck Out 💰 @wolf_millionaire 💰for our GUIDES To GROW Followers & Make MONEY @wolf_millionaire\n\nCLICK LINK IN BIO 🔥\n\nFREE GUIDE-> 🚨 www.WolfMillionaire.com 🚨\n\nCheck Out @wolf_millionaire \n#WolfMillionaire\nPhoto by @zerotosixtylifestyle \n#AstonMartin #DB11 #AstonMartinDB11 #MadWhips",
      "localization": null,
      "date": "2017-04-28T05:00:00.000Z",
      "numberLikes": 2581,
      "filename": "18162122_431354633904152_2396566213292457984_n.jpg"
    },
    {
      "url": "https://www.instagram.com/p/BTcvz-dBGTd/?taken-by=madwhips_british",
      "urlImage": "https://scontent-lga3-1.cdninstagram.com/vp/af6fed00f91d5034e9c1f871d241b947/5CAFCE4D/t51.2885-15/sh0.08/e35/s640x640/28764473_287993655066321_6675160681643245568_n.jpg",
      "isVideo": false,
      "multipleImage": false,
      "tags": [
        "#WolfMillionaire",
        "#Bentley",
        "#Continental",
        "#BentleyContinental",
        "#MadWhips"
      ],
      "mentions": [
        "@wolf_millionaire",
        "@wolf_millionaire",
        "@wolf_millionaire",
        "@supercarsinmanchester",
        "@supercarsinmanchester",
        "@wolf_millionaire"
      ],
      "description": "Bentley Continental GTC \nCheck Out 💰 @wolf_millionaire 💰for our GUIDES To GROW Followers & Make MONEY @wolf_millionaire\n\nCLICK LINK IN BIO 🔥\n\nFREE GUIDE-> 🚨 www.WolfMillionaire.com 🚨\n\nCheck Out @wolf_millionaire \n#WolfMillionaire\nPhoto by @supercarsinmanchester \n#Bentley #Continental #BentleyContinental #MadWhips",
      "localization": null,
      "date": "2017-04-28T05:00:00.000Z",
      "numberLikes": 1867,
      "filename": "18095257_949671195135551_5911511656713682944_n.jpg"
    },
    {
      "url": "https://www.instagram.com/p/BTaWrv6h5NW/?taken-by=madwhips_british",
      "urlImage": "https://scontent-lga3-1.cdninstagram.com/vp/8d93c29e175c6cca770e29dc52e5c004/5CA89ACE/t51.2885-15/sh0.08/e35/s640x640/29089887_1535586603227606_4140521745209622528_n.jpg",
      "isVideo": false,
      "multipleImage": false,
      "tags": [
        "#WolfMillionaire",
        "#RollsRoyce",
        "#Wraith",
        "#RollsRoyceWraith",
        "#MadWhips"
      ],
      "mentions": [
        "@wolf_millionaire",
        "@wolf_millionaire",
        "@wolf_millionaire",
        "@cologne_cars_photography",
        "@cologne_cars_photography",
        "@wolf_millionaire"
      ],
      "description": "Rolls Royce Wraith \nCheck Out 💰 @wolf_millionaire 💰for our GUIDES To GROW Followers & Make MONEY @wolf_millionaire\n\nCLICK LINK IN BIO 🔥\n\nFREE GUIDE-> 🚨 www.WolfMillionaire.com 🚨\n\nCheck Out @wolf_millionaire \n#WolfMillionaire\nPhoto by @cologne_cars_photography\n#RollsRoyce #Wraith #RollsRoyceWraith #MadWhips",
      "localization": null,
      "date": "2017-04-27T05:00:00.000Z",
      "numberLikes": 1318,
      "filename": "18094802_1890109807913606_5015903781703909376_n.jpg"
    },
    {
      "url": "https://www.instagram.com/p/BTaKIDiBVJe/?taken-by=madwhips_british",
      "urlImage": "https://scontent-lga3-1.cdninstagram.com/vp/86ff96057d6a4efde71b5d8ce505fc45/5CAD9D77/t51.2885-15/sh0.08/e35/p640x640/28765542_1425192947592279_5423754447362719744_n.jpg",
      "isVideo": false,
      "multipleImage": false,
      "tags": [
        "#WolfMillionaire",
        "#AstonMartin",
        "#DB11",
        "#AstonMartindb11",
        "#MadWhips"
      ],
      "mentions": [
        "@wolf_millionaire",
        "@wolf_millionaire",
        "@wolf_millionaire",
        "@speed",
        "@speed.exclusive",
        "@wolf_millionaire"
      ],
      "description": "Aston Martin DB11 \nCheck Out 💰 @wolf_millionaire 💰for our GUIDES To GROW Followers & Make MONEY @wolf_millionaire\n\nCLICK LINK IN BIO 🔥\n\nFREE GUIDE-> 🚨 www.WolfMillionaire.com 🚨\n\nCheck Out @wolf_millionaire \n#WolfMillionaire\nPhoto by @speed.exclusive \n#AstonMartin ##DB11 #AstonMartindb11 #MadWhips",
      "localization": null,
      "date": "2017-04-27T05:00:00.000Z",
      "numberLikes": 2658,
      "filename": "18011290_682401751943622_1827742363812888576_n.jpg"
    },
    {
      "url": "https://www.instagram.com/p/BTZW960BmZ-/?taken-by=madwhips_british",
      "urlImage": "https://scontent-lga3-1.cdninstagram.com/vp/753b6e55194dc723b1ef7bdf30f81538/5CA2CBFE/t51.2885-15/sh0.08/e35/s640x640/28766344_436895866739514_5895724993316126720_n.jpg",
      "isVideo": false,
      "multipleImage": false,
      "tags": [
        "#WolfMillionaire",
        "#McLaren",
        "#MadWhips"
      ],
      "mentions": [
        "@wolf_millionaire",
        "@wolf_millionaire",
        "@wolf_millionaire",
        "@k_cars",
        "@k_cars",
        "@wolf_millionaire"
      ],
      "description": "McLaren \nCheck Out 💰 @wolf_millionaire 💰for our GUIDES To GROW Followers & Make MONEY @wolf_millionaire\n\nCLICK LINK IN BIO 🔥\n\nFREE GUIDE-> 🚨 www.WolfMillionaire.com 🚨\n\nCheck Out @wolf_millionaire \n#WolfMillionaire\nPhoto by @k_cars \n#McLaren #MadWhips",
      "localization": null,
      "date": "2017-04-27T05:00:00.000Z",
      "numberLikes": 1829,
      "filename": "18096005_422176424841847_5639260869595496448_n.jpg"
    },
    {
      "url": "https://www.instagram.com/p/BTZGtoEBxpF/?taken-by=madwhips_british",
      "urlImage": "https://scontent-lga3-1.cdninstagram.com/vp/e1f8569e782851e8fbd6ff2eed35521b/5CB0EDDB/t51.2885-15/sh0.08/e35/s640x640/28752852_1633650096671858_2640243248710287360_n.jpg",
      "isVideo": false,
      "multipleImage": false,
      "tags": [
        "#WolfMillionaire",
        "#Bentley",
        "#FlyingSpur",
        "#BentleyFlyingSpur",
        "#MadWhips"
      ],
      "mentions": [
        "@wolf_millionaire",
        "@wolf_millionaire",
        "@wolf_millionaire",
        "@riviera_supercars",
        "@riviera_supercars",
        "@wolf_millionaire"
      ],
      "description": "Bentley Flying Spur \nCheck Out 💰 @wolf_millionaire 💰for our GUIDES To GROW Followers & Make MONEY @wolf_millionaire\n\nCLICK LINK IN BIO 🔥\n\nFREE GUIDE-> 🚨 www.WolfMillionaire.com 🚨\n\nCheck Out @wolf_millionaire \n#WolfMillionaire\nPhoto by @riviera_supercars \n#Bentley #FlyingSpur #BentleyFlyingSpur #MadWhips",
      "localization": null,
      "date": "2017-04-27T05:00:00.000Z",
      "numberLikes": 639,
      "filename": "18094554_289095058196423_4753870953711140864_n.jpg"
    },
    {
      "url": "https://www.instagram.com/p/BTXzBAuhJ28/?taken-by=madwhips_british",
      "urlImage": "https://scontent-lga3-1.cdninstagram.com/vp/e69dabc6958b4a59ce7875e4da719885/5C9644E3/t51.2885-15/sh0.08/e35/s640x640/28752050_928060817367726_2745720885221523456_n.jpg",
      "isVideo": false,
      "multipleImage": false,
      "tags": [
        "#WolfMillionaire",
        "#RollsRoyce",
        "#Wraith",
        "#RollsRoyceWraith",
        "#MadWhips"
      ],
      "mentions": [
        "@wolf_millionaire",
        "@wolf_millionaire",
        "@wolf_millionaire",
        "@_mu57afa_",
        "@_mu57afa_",
        "@wolf_millionaire"
      ],
      "description": "Rolls Royce Wraith \nCheck Out 💰 @wolf_millionaire 💰for our GUIDES To GROW Followers & Make MONEY @wolf_millionaire\n\nCLICK LINK IN BIO 🔥\n\nFREE GUIDE-> 🚨 www.WolfMillionaire.com 🚨\n\nCheck Out @wolf_millionaire \n#WolfMillionaire\nPhoto by @_mu57afa_\n#RollsRoyce #Wraith #RollsRoyceWraith #MadWhips",
      "localization": null,
      "date": "2017-04-26T05:00:00.000Z",
      "numberLikes": 1421,
      "filename": "18011577_305624589870380_2844956890574618624_n.jpg"
    },
    {
      "url": "https://www.instagram.com/p/BTXl9g0h2hv/?taken-by=madwhips_british",
      "urlImage": "https://scontent-lga3-1.cdninstagram.com/vp/e98ded0ed7af0aaee6d2c791bafcdf4a/5C8ED0DE/t51.2885-15/sh0.08/e35/p640x640/28752814_178702796100420_4916958751795183616_n.jpg",
      "isVideo": false,
      "multipleImage": false,
      "tags": [
        "#WolfMillionaire",
        "#AstonMartin",
        "#Vantage",
        "#AstonMartinvantage",
        "#MadWhips"
      ],
      "mentions": [
        "@wolf_millionaire",
        "@wolf_millionaire",
        "@wolf_millionaire",
        "@jack",
        "@jack.wheatley",
        "@wolf_millionaire"
      ],
      "description": "Aston Martin Vantage V12 \nCheck Out 💰 @wolf_millionaire 💰for our GUIDES To GROW Followers & Make MONEY @wolf_millionaire\n\nCLICK LINK IN BIO 🔥\n\nFREE GUIDE-> 🚨 www.WolfMillionaire.com 🚨\n\nCheck Out @wolf_millionaire \n#WolfMillionaire\nPhoto by @jack.wheatley \n#AstonMartin #Vantage #AstonMartinvantage #MadWhips",
      "localization": null,
      "date": "2017-04-26T05:00:00.000Z",
      "numberLikes": 1764,
      "filename": "18013414_102140050355775_5067268154590232576_n.jpg"
    },
    {
      "url": "https://www.instagram.com/p/BTWzk3_hDJP/?taken-by=madwhips_british",
      "urlImage": "https://scontent-lga3-1.cdninstagram.com/vp/892afd372b745317d3ce1780440baaef/5C8D17D3/t51.2885-15/sh0.08/e35/s640x640/29093652_416880782114213_7336660205859504128_n.jpg",
      "isVideo": false,
      "multipleImage": false,
      "tags": [
        "#WolfMillionaire",
        "#Lotus",
        "#evora",
        "#LotusEvora",
        "#MadWhips"
      ],
      "mentions": [
        "@wolf_millionaire",
        "@wolf_millionaire",
        "@wolf_millionaire",
        "@exotic_cars_bc",
        "@exotic_cars_bc",
        "@wolf_millionaire"
      ],
      "description": "Evora \nCheck Out 💰 @wolf_millionaire 💰for our GUIDES To GROW Followers & Make MONEY @wolf_millionaire\n\nCLICK LINK IN BIO 🔥\n\nFREE GUIDE-> 🚨 www.WolfMillionaire.com 🚨\n\nCheck Out @wolf_millionaire \n#WolfMillionaire\nPhoto by @exotic_cars_bc \n#Lotus #evora #LotusEvora #MadWhips",
      "localization": null,
      "date": "2017-04-26T05:00:00.000Z",
      "numberLikes": 874,
      "filename": "18095944_1299447246842454_6908619027791216640_n.jpg"
    },
    {
      "url": "https://www.instagram.com/p/BTWg1E5hBvA/?taken-by=madwhips_british",
      "urlImage": "https://scontent-lga3-1.cdninstagram.com/vp/18897035e2bca13e2acf386d87d4cf74/5C8EA225/t51.2885-15/sh0.08/e35/s640x640/29089111_154944041827224_6580832956326084608_n.jpg",
      "isVideo": false,
      "multipleImage": false,
      "tags": [
        "#WolfMillionaire",
        "#Jaguar",
        "#project7",
        "#jaguarproject7",
        "#MadWhips"
      ],
      "mentions": [
        "@wolf_millionaire",
        "@wolf_millionaire",
        "@wolf_millionaire",
        "@austin_ables",
        "@austin_ables",
        "@wolf_millionaire"
      ],
      "description": "Jaguar Project 7 \nCheck Out 💰 @wolf_millionaire 💰for our GUIDES To GROW Followers & Make MONEY @wolf_millionaire\n\nCLICK LINK IN BIO 🔥\n\nFREE GUIDE-> 🚨 www.WolfMillionaire.com 🚨\n\nCheck Out @wolf_millionaire \n#WolfMillionaire\nPhoto by @austin_ables \n#Jaguar #project7 #jaguarproject7 #MadWhips",
      "localization": null,
      "date": "2017-04-26T05:00:00.000Z",
      "numberLikes": 1666,
      "filename": "18094554_761299644048422_5703130529390395392_n.jpg"
    },
    {
      "url": "https://www.instagram.com/p/BTVOclIhK55/?taken-by=madwhips_british",
      "urlImage": "https://scontent-lga3-1.cdninstagram.com/vp/236ea74b5f23407db1d7a05839e88737/5C8DA2B2/t51.2885-15/sh0.08/e35/s640x640/28766490_159217804794317_1850779619200860160_n.jpg",
      "isVideo": false,
      "multipleImage": false,
      "tags": [
        "#WolfMillionaire",
        "#McLaren",
        "#570S",
        "#McLaren570s",
        "#MadWhips"
      ],
      "mentions": [
        "@wolf_millionaire",
        "@wolf_millionaire",
        "@wolf_millionaire",
        "@supercars_sighted",
        "@supercars_sighted",
        "@wolf_millionaire"
      ],
      "description": "McLaren 570s \nCheck Out 💰 @wolf_millionaire 💰for our GUIDES To GROW Followers & Make MONEY @wolf_millionaire\n\nCLICK LINK IN BIO 🔥\n\nFREE GUIDE-> 🚨 www.WolfMillionaire.com 🚨\n\nCheck Out @wolf_millionaire \n#WolfMillionaire\nPhoto by @supercars_sighted \n#McLaren #570S #McLaren570s #MadWhips",
      "localization": null,
      "date": "2017-04-25T05:00:00.000Z",
      "numberLikes": 1058,
      "filename": "18096202_228162647666130_3192376687773876224_n.jpg"
    },
    {
      "url": "https://www.instagram.com/p/BTVAs_8BBjU/?taken-by=madwhips_british",
      "urlImage": "https://scontent-lga3-1.cdninstagram.com/vp/acf2cc0d5b7b6936960c4c442c3eb1b9/5C8F1001/t51.2885-15/sh0.08/e35/s640x640/28763463_1465985853511936_7252029404300181504_n.jpg",
      "isVideo": false,
      "multipleImage": false,
      "tags": [
        "#WolfMillionaire",
        "#AstonMartin",
        "#DB11",
        "#AstonMartindb11",
        "#MadWhips"
      ],
      "mentions": [
        "@wolf_millionaire",
        "@wolf_millionaire",
        "@wolf_millionaire",
        "@james_hphotography",
        "@james_hphotography",
        "@wolf_millionaire"
      ],
      "description": "Aston Martin DB11 \nCheck Out 💰 @wolf_millionaire 💰for our GUIDES To GROW Followers & Make MONEY @wolf_millionaire\n\nCLICK LINK IN BIO 🔥\n\nFREE GUIDE-> 🚨 www.WolfMillionaire.com 🚨\n\nCheck Out @wolf_millionaire \n#WolfMillionaire\nPhoto by @james_hphotography \n#AstonMartin #DB11 #AstonMartindb11 #MadWhips",
      "localization": null,
      "date": "2017-04-25T05:00:00.000Z",
      "numberLikes": 2334,
      "filename": "18013525_1887866748149235_1753896027565326336_n.jpg"
    },
    {
      "url": "https://www.instagram.com/p/BTUNKLPhxwO/?taken-by=madwhips_british",
      "urlImage": "https://scontent-lga3-1.cdninstagram.com/vp/b22097fee57078309ec3cc3ca05396e6/5C90FE8E/t51.2885-15/e35/s480x480/29090529_1896926030341244_7913375018363387904_n.jpg",
      "isVideo": false,
      "multipleImage": false,
      "tags": [
        "#WolfMillionaire",
        "#RollsRoyce",
        "#Wraith",
        "#RollsRoyceWraith",
        "#MadWhips"
      ],
      "mentions": [
        "@wolf_millionaire",
        "@wolf_millionaire",
        "@wolf_millionaire",
        "@delhicars",
        "@wolf_millionaire",
        "@delhicars"
      ],
      "description": "Rolls Royce Wraith \nCheck Out 💰 @wolf_millionaire 💰for our GUIDES To GROW Followers & Make MONEY @wolf_millionaire\n\nCLICK LINK IN BIO 🔥\n\nFREE GUIDE-> 🚨 www.WolfMillionaire.com 🚨\n\nCheck Out @wolf_millionaire \n#WolfMillionaire\nPhoto by @delhicars \n#RollsRoyce #Wraith #RollsRoyceWraith #MadWhips",
      "localization": null,
      "date": "2017-04-25T05:00:00.000Z",
      "numberLikes": 1486,
      "filename": "18012115_1720138558283207_3975666056982167552_n.jpg"
    }
  ]
}