{
    "alias": "Scott Schuman",
    "username": "thesartorialist",
    "bio": "The Sartorialist\nFounded in 2005\n2012 CFDA Media Award\nAuthor of three books",
    "prof_img": "https://instagram.fzty1-2.fna.fbcdn.net/vp/ad08c23a86dd98b7fe4563f39adcb7e2/5CA65FD3/t51.2885-19/924689_857685700974311_1011916035_a.jpg",
    "num_of_posts": 4141,
    "followers": 1077274,
    "following": 527,
    "bio_url": "www.thesartorialist.com",
    "isprivate": false,
    "scrapped": "2018-11-29 09:49:59",
    "posts": [
        {
            "caption": "",
            "location": {
                "location_url": "https://www.instagram.com/explore/locations/212988663/new-york-new-york/",
                "location_name": "New York, New York",
                "location_id": "212988663",
                "latitude": 40.7142,
                "longitude": -74.0064
            },
            "img": null,
            "preview_img": null,
            "date": "2018-11-28T16:13:24.000Z",
            "tags": [],
            "likes": 7248,
            "url": "https://www.instagram.com/p/BquvU3RFh7J/",
            "comments": {
                "count": 25,
                "list": [
                    {
                        "user": "thesartorialist",
                        "comment": "I saw this young lady in Milan and there was just something so unselfconscious and elegant about how she wore her clothes, her hair and even the way she held her cigarette (even though I know cigarettes are very very bad) I took this photo and then asked to shoot her right after but once she was aware she was being photographed it wasn\u2019t the same nonchalance. She\u2019s maybe one of those special breed that has to be \u201ccaptured\u201d in the moment. (I also put a better crop in Stories to get a better sense of her grace)"
                    }
                ]
            },
            "mentions": []
        },
        {
            "caption": "",
            "location": {
                "location_url": "https://www.instagram.com/explore/locations/212988663/new-york-new-york/",
                "location_name": "New York, New York",
                "location_id": "212988663",
                "latitude": 40.7142,
                "longitude": -74.0064
            },
            "img": null,
            "preview_img": null,
            "date": "2018-10-29T15:00:09.000Z",
            "tags": [],
            "likes": 5551,
            "url": "https://www.instagram.com/p/BphXGDPl1Tf/",
            "comments": {
                "count": 25,
                "list": [
                    {
                        "user": "thesartorialist",
                        "comment": "Before @fendi, Milan (Check Stories for a longer crop)"
                    }
                ]
            },
            "mentions": []
        },
        {
            "caption": "",
            "location": {
                "location_url": "https://www.instagram.com/explore/locations/212988663/new-york-new-york/",
                "location_name": "New York, New York",
                "location_id": "212988663",
                "latitude": 40.7142,
                "longitude": -74.0064
            },
            "img": null,
            "preview_img": null,
            "date": "2018-11-20T14:22:13.000Z",
            "tags": [],
            "likes": 4133,
            "url": "https://www.instagram.com/p/BqZ8PiJFG3T/",
            "comments": {
                "count": 25,
                "list": [
                    {
                        "user": "thesartorialist",
                        "comment": "Sweater weather doesn\u2019t always mean being over-bundled, Paris"
                    }
                ]
            },
            "mentions": [
                "aka.kimbui"
            ]
        },
        {
            "caption": "",
            "location": {
                "location_url": "https://www.instagram.com/explore/locations/212988663/new-york-new-york/",
                "location_name": "New York, New York",
                "location_id": "212988663",
                "latitude": 40.7142,
                "longitude": -74.0064
            },
            "img": null,
            "preview_img": null,
            "date": "2018-11-05T14:58:14.000Z",
            "tags": [],
            "likes": 9148,
            "url": "https://www.instagram.com/p/BpzYcJol0E6/",
            "comments": {
                "count": 25,
                "list": [
                    {
                        "user": "thesartorialist",
                        "comment": "Like a Cubist painting in the center of Milan!"
                    }
                ]
            },
            "mentions": [
                "andrewcoconut"
            ]
        },
        {
            "caption": "",
            "location": {
                "location_url": "https://www.instagram.com/explore/locations/212988663/new-york-new-york/",
                "location_name": "New York, New York",
                "location_id": "212988663",
                "latitude": 40.7142,
                "longitude": -74.0064
            },
            "img": null,
            "preview_img": null,
            "date": "2018-11-02T14:07:08.000Z",
            "tags": [],
            "likes": 10201,
            "url": "https://www.instagram.com/p/BprkNR4lhBN/",
            "comments": {
                "count": 25,
                "list": [
                    {
                        "user": "thesartorialist",
                        "comment": "51 and fun today!"
                    }
                ]
            },
            "mentions": [
                "thesartorialist"
            ]
        },
        {
            "caption": "",
            "location": {
                "location_url": "https://www.instagram.com/explore/locations/212988663/new-york-new-york/",
                "location_name": "New York, New York",
                "location_id": "212988663",
                "latitude": 40.7142,
                "longitude": -74.0064
            },
            "img": null,
            "preview_img": null,
            "date": "2018-11-22T19:39:01.000Z",
            "tags": [],
            "likes": 4011,
            "url": "https://www.instagram.com/p/BqfqFnulX2F/",
            "comments": {
                "count": 25,
                "list": [
                    {
                        "user": "thesartorialist",
                        "comment": "The perfect Thanksgiving Day jacket ! Thanks @driesvannoten"
                    }
                ]
            },
            "mentions": [
                "antoniopicardi",
                "driesvannoten"
            ]
        },
        {
            "caption": "",
            "location": {
                "location_url": "https://www.instagram.com/explore/locations/212988663/new-york-new-york/",
                "location_name": "New York, New York",
                "location_id": "212988663",
                "latitude": 40.7142,
                "longitude": -74.0064
            },
            "img": null,
            "preview_img": null,
            "date": "2018-11-06T17:35:15.000Z",
            "tags": [],
            "likes": 5927,
            "url": "https://www.instagram.com/p/Bp2PNGel2qH/",
            "comments": {
                "count": 25,
                "list": [
                    {
                        "user": "thesartorialist",
                        "comment": "Such a funny mix of stripes and pattern! Milan"
                    }
                ]
            },
            "mentions": []
        },
        {
            "caption": "",
            "location": {
                "location_url": "https://www.instagram.com/explore/locations/212988663/new-york-new-york/",
                "location_name": "New York, New York",
                "location_id": "212988663",
                "latitude": 40.7142,
                "longitude": -74.0064
            },
            "img": null,
            "preview_img": null,
            "date": "2018-10-31T13:05:18.000Z",
            "tags": [],
            "likes": 28964,
            "url": "https://www.instagram.com/p/BpmTiryl2TE/",
            "comments": {
                "count": 25,
                "list": [
                    {
                        "user": "thesartorialist",
                        "comment": "I\u2019m sure they\u2019re talking about food and this is the part of the recipe that you add a pinch of salt"
                    }
                ]
            },
            "mentions": []
        },
        {
            "caption": "",
            "location": {
                "location_url": "https://www.instagram.com/explore/locations/212988663/new-york-new-york/",
                "location_name": "New York, New York",
                "location_id": "212988663",
                "latitude": 40.7142,
                "longitude": -74.0064
            },
            "img": null,
            "preview_img": null,
            "date": "2018-11-12T14:40:30.000Z",
            "tags": [],
            "likes": 7361,
            "url": "https://www.instagram.com/p/BqFX-aoFzzv/",
            "comments": {
                "count": 25,
                "list": [
                    {
                        "user": "thesartorialist",
                        "comment": "It\u2019s finally and consistently sweater weather!! Milan"
                    }
                ]
            },
            "mentions": []
        },
        {
            "caption": "",
            "location": {
                "location_url": "https://www.instagram.com/explore/locations/212988663/new-york-new-york/",
                "location_name": "New York, New York",
                "location_id": "212988663",
                "latitude": 40.7142,
                "longitude": -74.0064
            },
            "img": null,
            "preview_img": null,
            "date": "2018-11-26T15:49:06.000Z",
            "tags": [],
            "likes": 11734,
            "url": "https://www.instagram.com/p/Bqpi9G-FDyd/",
            "comments": {
                "count": 25,
                "list": [
                    {
                        "user": "thesartorialist",
                        "comment": "It feels so 80s but looks so right now, Milan"
                    }
                ]
            },
            "mentions": []
        },
        {
            "caption": "",
            "location": {
                "location_url": "https://www.instagram.com/explore/locations/212988663/new-york-new-york/",
                "location_name": "New York, New York",
                "location_id": "212988663",
                "latitude": "",
                "longitude": ""
            },
            "img": null,
            "preview_img": null,
            "date": "2018-11-27T15:28:41.000Z",
            "tags": [],
            "likes": 12345,
            "url": "https://www.instagram.com/p/BqsFagOFSOp/",
            "comments": {
                "count": 25,
                "list": [
                    {
                        "user": "thesartorialist",
                        "comment": "This is a man that knows how to wear a jacket with the ease of a cardigan! The ever chic Mr. Pierre Maheo of @officinegenerale"
                    }
                ]
            },
            "mentions": [
                "officinegenerale"
            ]
        },
        {
            "caption": "",
            "location": {
                "location_url": "https://www.instagram.com/explore/locations/212988663/new-york-new-york/",
                "location_name": "New York, New York",
                "location_id": "212988663",
                "latitude": 40.7142,
                "longitude": -74.0064
            },
            "img": null,
            "preview_img": null,
            "date": "2018-11-09T15:53:47.000Z",
            "tags": [],
            "likes": 11172,
            "url": "https://www.instagram.com/p/Bp9x-gIFrMX/",
            "comments": {
                "count": 25,
                "list": [
                    {
                        "user": "thesartorialist",
                        "comment": "Knightsbridge, London\nOctober, 2018"
                    }
                ]
            },
            "mentions": []
        }
    ]
}