{
    "alias": "Liam Miscellaneous \ud83d\udca7",
    "username": "waverider_",
    "bio": "Walmart version of life\ud83d\udc83\ud83c\udffd\ud83d\udc84\ud83c\udf5c Trying to bring a little bit of humour to da big thicc world\ud83c\udf2c\ud83c\udf0f\u2728 Join the movement!!! \ud83c\udf08EGGPLANT FAM \ud83c\udf46",
    "prof_img": "https://scontent-lga3-1.cdninstagram.com/vp/f1fadfb9d32503585da842ab004a7e2a/5CB1E744/t51.2885-19/s320x320/44852076_2272447016318166_90185993864347648_n.jpg",
    "num_of_posts": 650,
    "followers": 1194756,
    "following": 6094,
    "bio_url": "youtu.be/1XtPmz-sp3U",
    "isprivate": false,
    "scrapped": "2018-11-28 23:19:36",
    "posts": [
        {
            "caption": "Thought I would get into the Christmas spirit... Like this if you are excited for Christmas \ud83c\udf85",
            "location": {
                "location_url": "",
                "location_name": "",
                "location_id": 0,
                "latitude": "",
                "longitude": ""
            },
            "img": "https://scontent-lga3-1.cdninstagram.com/vp/403c11260c40c1e62fcd4841676473b4/5CA65FA3/t51.2885-15/e15/21296945_114690889249187_2845484694810656768_n.jpg",
            "preview_img": "https://scontent-lga3-1.cdninstagram.com/vp/403c11260c40c1e62fcd4841676473b4/5CA65FA3/t51.2885-15/e15/21296945_114690889249187_2845484694810656768_n.jpg",
            "date": "2014-12-12T22:43:49.000Z",
            "tags": [],
            "likes": 527654,
            "url": "https://www.instagram.com/p/whhwK2NqnB/",
            "comments": {
                "count": 25,
                "list": []
            },
            "mentions": []
        },
        {
            "caption": "Oh na na what's ma name? I did this photo months ago but I never posted it, so here it is!!! I lost this wig in the ocean... Like if you cried \ud83d\ude2d",
            "location": {
                "location_url": "",
                "location_name": "",
                "location_id": 0,
                "latitude": "",
                "longitude": ""
            },
            "img": "https://scontent-lga3-1.cdninstagram.com/vp/e37390fe74f9c03900311484e5ca812a/5CA0A2BC/t51.2885-15/e15/21371823_272379339928619_5325714547451887616_n.jpg",
            "preview_img": "https://scontent-lga3-1.cdninstagram.com/vp/e37390fe74f9c03900311484e5ca812a/5CA0A2BC/t51.2885-15/e15/21371823_272379339928619_5325714547451887616_n.jpg",
            "date": "2015-03-25T11:38:22.000Z",
            "tags": [],
            "likes": 322608,
            "url": "https://www.instagram.com/p/0pjebatqqs/",
            "comments": {
                "count": 25,
                "list": []
            },
            "mentions": []
        },
        {
            "caption": "I normally dress up as female celebrities but @tyleroakley is a queen \ud83d\udc51 it took me 45 minutes to stick cotton candy on my head... Tag a friend and I'll try like your photo",
            "location": {
                "location_url": "",
                "location_name": "",
                "location_id": 0,
                "latitude": "",
                "longitude": ""
            },
            "img": "https://scontent-lga3-1.cdninstagram.com/vp/bb30a5c12903c95e4c6d04a3c042ab38/5CAC0CDA/t51.2885-15/e15/21371994_116918925665202_2141746787168288768_n.jpg",
            "preview_img": "https://scontent-lga3-1.cdninstagram.com/vp/bb30a5c12903c95e4c6d04a3c042ab38/5CAC0CDA/t51.2885-15/e15/21371994_116918925665202_2141746787168288768_n.jpg",
            "date": "2014-12-22T12:48:03.000Z",
            "tags": [],
            "likes": 519869,
            "url": "https://www.instagram.com/p/w6NhZmNqnk/",
            "comments": {
                "count": 25,
                "list": []
            },
            "mentions": []
        },
        {
            "caption": "YOU CAN CALL ME QUEEN BEY \ud83d\udc51 I had to use duct tape to make my shoes... I guess you could say it gave me a free wax \ud83d\ude13 like if you cry \ud83d\ude13 collaboration with @ifunny.co",
            "location": {
                "location_url": "",
                "location_name": "",
                "location_id": 0,
                "latitude": "",
                "longitude": ""
            },
            "img": "https://scontent-lga3-1.cdninstagram.com/vp/426d4bbfb6151c239d97bca6bde3fce8/5C944D2B/t51.2885-15/e15/21296998_1374104012702534_602909410020294656_n.jpg",
            "preview_img": "https://scontent-lga3-1.cdninstagram.com/vp/426d4bbfb6151c239d97bca6bde3fce8/5C944D2B/t51.2885-15/e15/21296998_1374104012702534_602909410020294656_n.jpg",
            "date": "2015-05-03T11:45:15.000Z",
            "tags": [],
            "likes": 294725,
            "url": "https://www.instagram.com/p/2N_RAOtqgK/",
            "comments": {
                "count": 25,
                "list": []
            },
            "mentions": []
        },
        {
            "caption": "Actual photo of me in yo mans shirt \ud83d\udc83\ud83c\udffd\ud83c\udf08\u2728",
            "location": {
                "location_url": "https://www.instagram.com/explore/locations/212999109/los-angeles-california/",
                "location_name": "Los Angeles, California",
                "location_id": "212999109",
                "latitude": 34.0522,
                "longitude": -118.243
            },
            "img": "https://scontent-lga3-1.cdninstagram.com/vp/0e291bbe2fcdbba4eea29fb5cff29854/5CA89905/t51.2885-15/e35/21373475_1961660184090366_4587991783366983680_n.jpg",
            "preview_img": "https://scontent-lga3-1.cdninstagram.com/vp/fc33668c219b31ce0375d8d80865ece6/5CA5C4BF/t51.2885-15/sh0.08/e35/s640x640/21373475_1961660184090366_4587991783366983680_n.jpg",
            "date": "2017-03-25T18:03:22.000Z",
            "tags": [],
            "likes": 39039,
            "url": "https://www.instagram.com/p/BSEgn7bgWCb/",
            "comments": {
                "count": 25,
                "list": []
            },
            "mentions": [
                "waverider_",
                "selenagomez"
            ]
        },
        {
            "caption": "There's a snake in my booty...\ud83d\udc0d",
            "location": {
                "location_url": "",
                "location_name": "",
                "location_id": 0,
                "latitude": "",
                "longitude": ""
            },
            "img": "https://scontent-lga3-1.cdninstagram.com/vp/1e9e6f1dccce33cc62fa7415d1a4b816/5CAC09DF/t51.2885-15/e35/45858382_501720933675544_8901172213400690419_n.jpg",
            "preview_img": "https://scontent-lga3-1.cdninstagram.com/vp/c8288976b22ecc32a91aaf32ca75756f/5C8C7A3A/t51.2885-15/sh0.08/e35/s640x640/45858382_501720933675544_8901172213400690419_n.jpg",
            "date": "2018-11-25T12:29:16.000Z",
            "tags": [],
            "likes": 61102,
            "url": "https://www.instagram.com/p/BqmnSjkgvTz/",
            "comments": {
                "count": 25,
                "list": []
            },
            "mentions": [
                "kyliejenner"
            ]
        },
        {
            "caption": "My dad wouldn't let me use real fire... Like if you cry \ud83d\ude2d. Ps, the circle is actually a donut TAG 3 FRIENDS\u2764\ufe0f",
            "location": {
                "location_url": "",
                "location_name": "",
                "location_id": 0,
                "latitude": "",
                "longitude": ""
            },
            "img": "https://scontent-lga3-1.cdninstagram.com/vp/45275712bca31506bc528fc27a75086d/5CB1A21A/t51.2885-15/e15/21373106_166880600532017_4847945533655875584_n.jpg",
            "preview_img": "https://scontent-lga3-1.cdninstagram.com/vp/45275712bca31506bc528fc27a75086d/5CB1A21A/t51.2885-15/e15/21373106_166880600532017_4847945533655875584_n.jpg",
            "date": "2014-11-25T12:49:27.000Z",
            "tags": [],
            "likes": 521557,
            "url": "https://www.instagram.com/p/v0sOEoNqqK/",
            "comments": {
                "count": 25,
                "list": []
            },
            "mentions": []
        },
        {
            "caption": "Actual photo of me reclaiming my #Reputation \ud83d\udc51\ud83c\udf46... Who likes my new eggplant tattoo? I need a name for it??? Comment some ideas \ud83d\ude1c\u2728",
            "location": {
                "location_url": "",
                "location_name": "",
                "location_id": 0,
                "latitude": "",
                "longitude": ""
            },
            "img": "https://scontent-lga3-1.cdninstagram.com/vp/d73b75fbff809f2e388af56cc067252d/5CA8F37B/t51.2885-15/e35/21436154_858161494334730_54486118325813248_n.jpg",
            "preview_img": "https://scontent-lga3-1.cdninstagram.com/vp/cbf37c87c7845f08319dd40a160e14bc/5CAE8935/t51.2885-15/sh0.08/e35/s640x640/21436154_858161494334730_54486118325813248_n.jpg",
            "date": "2017-09-09T13:10:55.000Z",
            "tags": [
                "#Reputation"
            ],
            "likes": 28181,
            "url": "https://www.instagram.com/p/BY0ks5kgXiY/",
            "comments": {
                "count": 25,
                "list": []
            },
            "mentions": [
                "taylorswift"
            ]
        },
        {
            "caption": "Hello kiddies sorry I haven't posted in so long... Mother hood is exhausting \ud83d\ude05 Blue Ivy & the twins are doing well \ud83d\ude0f\u2728Ps. I don't have a baby so I just decided to use a bucket of blue paint...u feel??? bc Blue Ivy \ud83d\ude1c\ud83d\udca6",
            "location": {
                "location_url": "",
                "location_name": "",
                "location_id": 0,
                "latitude": "",
                "longitude": ""
            },
            "img": "https://scontent-lga3-1.cdninstagram.com/vp/2d3d8863697ad7807b5f33808cc74ad9/5CB18875/t51.2885-15/e35/21296331_279128605916482_3111901271368400896_n.jpg",
            "preview_img": "https://scontent-lga3-1.cdninstagram.com/vp/1b023561def2f16bb4566c82b6848c3a/5C8AEE90/t51.2885-15/sh0.08/e35/s640x640/21296331_279128605916482_3111901271368400896_n.jpg",
            "date": "2017-09-03T10:38:21.000Z",
            "tags": [],
            "likes": 38846,
            "url": "https://www.instagram.com/p/BYk2eLEASoj/",
            "comments": {
                "count": 25,
                "list": []
            },
            "mentions": [
                "beyonce"
            ]
        },
        {
            "caption": "You can call me Queen Weave \ud83d\udc78\ud83c\udffc#beyonce",
            "location": {
                "location_url": "",
                "location_name": "",
                "location_id": 0,
                "latitude": "",
                "longitude": ""
            },
            "img": "https://scontent-lga3-1.cdninstagram.com/vp/f65cf73f94d8317b009dffab317bba89/5CAED8F2/t51.2885-15/e35/21296130_608232409565719_7950637488903553024_n.jpg",
            "preview_img": "https://scontent-lga3-1.cdninstagram.com/vp/43272d16ade16221c4b448c334f7ce76/5CA72D17/t51.2885-15/sh0.08/e35/s640x640/21296130_608232409565719_7950637488903553024_n.jpg",
            "date": "2017-05-06T10:00:35.000Z",
            "tags": [
                "#beyonce"
            ],
            "likes": 47188,
            "url": "https://www.instagram.com/p/BTvywoqAK_a/",
            "comments": {
                "count": 25,
                "list": []
            },
            "mentions": [
                "waverider_",
                "beyonce",
                "matthewvisual"
            ]
        },
        {
            "caption": "I literally don't even know what to caption this... TAG A FRIEND WHOS BOOTY IS POPPIN",
            "location": {
                "location_url": "",
                "location_name": "",
                "location_id": 0,
                "latitude": "",
                "longitude": ""
            },
            "img": "https://scontent-lga3-1.cdninstagram.com/vp/a74ccdd080ab83d2667075ac96efd66e/5C8BCDA2/t51.2885-15/e15/21372512_118608472134444_453117022503436288_n.jpg",
            "preview_img": "https://scontent-lga3-1.cdninstagram.com/vp/a74ccdd080ab83d2667075ac96efd66e/5C8BCDA2/t51.2885-15/e15/21372512_118608472134444_453117022503436288_n.jpg",
            "date": "2014-11-14T12:35:41.000Z",
            "tags": [],
            "likes": 550462,
            "url": "https://www.instagram.com/p/vYV5k3tqig/",
            "comments": {
                "count": 25,
                "list": []
            },
            "mentions": []
        },
        {
            "caption": "Please read the caption: When you can't afford a snake so you use your vacuum cleaner\ud83d\ude02... Anyway I would just like to let you guys know a little about what's gone on in my life lately!! After living in a very nasty and abusive environment for months and months I moved to my grandmas house, she helped me get on my feet and I have recently moved into an apartment!!! It is really nice to finally be away from the abuse and negativity, but I have been very caught up with trying to sort my life out and paying rent/food and other things! So I am sorry for my lack of photos and interaction with you all, it has been a very hard few months for me and I have tried my hardest to get out of it. It makes me very happy to have your support, I am very blessed to be able to share my creativity with you guys!!! I love posting a photo and reading through your lovely comments and making you guys laugh!! I haven't gone into too much detail about what has gone on in my life but I thought I better give you guys an explanation as you have become such a big part of my life it's only fair to share with you guys what has been going on! And I want you to know that no matter what you are going through right now you can get through it and I will truly try my hardest to help any of you who may be struggling!.. This photo is of Jennifer Lawrence and it was very awkward to take \ud83d\ude1d TAG A FRIEND who would like my booty",
            "location": {
                "location_url": "",
                "location_name": "",
                "location_id": 0,
                "latitude": "",
                "longitude": ""
            },
            "img": "https://scontent-lga3-1.cdninstagram.com/vp/a6dd34ef119f8af1e7af438eb7bb3bc7/5CB03756/t51.2885-15/e15/21296822_162137847671831_5260377211432599552_n.jpg",
            "preview_img": "https://scontent-lga3-1.cdninstagram.com/vp/a6dd34ef119f8af1e7af438eb7bb3bc7/5CB03756/t51.2885-15/e15/21296822_162137847671831_5260377211432599552_n.jpg",
            "date": "2015-05-25T05:19:11.000Z",
            "tags": [],
            "likes": 251170,
            "url": "https://www.instagram.com/p/3F8kkxtqib/",
            "comments": {
                "count": 25,
                "list": []
            },
            "mentions": []
        },
        {
            "caption": "This dude named Michael used to ride motorcycles \ud83d\ude02 I made my dress out of tape and I think it ripped half my skin off!!! Like if you cried! TAG 3 FRIENDS and I will try like your photos",
            "location": {
                "location_url": "",
                "location_name": "",
                "location_id": 0,
                "latitude": "",
                "longitude": ""
            },
            "img": "https://scontent-lga3-1.cdninstagram.com/vp/53aff20d74cc631a158ce88429ad3a21/5CA8A1B4/t51.2885-15/e15/21297033_1129545407179344_3123337158664912896_n.jpg",
            "preview_img": "https://scontent-lga3-1.cdninstagram.com/vp/53aff20d74cc631a158ce88429ad3a21/5CA8A1B4/t51.2885-15/e15/21297033_1129545407179344_3123337158664912896_n.jpg",
            "date": "2015-01-04T12:42:45.000Z",
            "tags": [],
            "likes": 467487,
            "url": "https://www.instagram.com/p/xbrQCMNquF/",
            "comments": {
                "count": 25,
                "list": []
            },
            "mentions": [
                "liamspersonal"
            ]
        },
        {
            "caption": "Comment where you are from!!! My booty and I want to know \ud83d\ude04",
            "location": {
                "location_url": "",
                "location_name": "",
                "location_id": 0,
                "latitude": "",
                "longitude": ""
            },
            "img": "https://scontent-lga3-1.cdninstagram.com/vp/133c3d6cb50fd6d8faf0bf09aa65a95a/5C9A37BE/t51.2885-15/e15/21372013_304579016617590_7485456315582513152_n.jpg",
            "preview_img": "https://scontent-lga3-1.cdninstagram.com/vp/133c3d6cb50fd6d8faf0bf09aa65a95a/5C9A37BE/t51.2885-15/e15/21372013_304579016617590_7485456315582513152_n.jpg",
            "date": "2015-02-18T13:19:34.000Z",
            "tags": [],
            "likes": 355270,
            "url": "https://www.instagram.com/p/zPnPACtqkb/",
            "comments": {
                "count": 25,
                "list": []
            },
            "mentions": []
        },
        {
            "caption": "In support of Miley Cyrus's @happyhippiefdn I have decided to dress up as her!!!! Like this photo if you think I have sexy teeth \ud83d\ude09\ud83d\ude09\ud83d\ude06",
            "location": {
                "location_url": "",
                "location_name": "",
                "location_id": 0,
                "latitude": "",
                "longitude": ""
            },
            "img": "https://scontent-lga3-1.cdninstagram.com/vp/24cdd3af65e53682faf5bd5cd48f38a7/5C91C8BA/t51.2885-15/e15/21373332_117905122265201_1098308611731357696_n.jpg",
            "preview_img": "https://scontent-lga3-1.cdninstagram.com/vp/24cdd3af65e53682faf5bd5cd48f38a7/5C91C8BA/t51.2885-15/e15/21373332_117905122265201_1098308611731357696_n.jpg",
            "date": "2015-06-19T06:17:31.000Z",
            "tags": [],
            "likes": 205917,
            "url": "https://www.instagram.com/p/4GbHxENqiO/",
            "comments": {
                "count": 25,
                "list": []
            },
            "mentions": []
        },
        {
            "caption": "I know it isn't Christmas anymore but you can still lick my candy cane...\ud83d\ude02tag somebody that would lick my candy cane \ud83d\udc45",
            "location": {
                "location_url": "",
                "location_name": "",
                "location_id": 0,
                "latitude": "",
                "longitude": ""
            },
            "img": "https://scontent-lga3-1.cdninstagram.com/vp/cb8b2d6f4c92d272faff70b46438c23b/5C8F8A01/t51.2885-15/e15/21296885_512510259090836_7917735956357054464_n.jpg",
            "preview_img": "https://scontent-lga3-1.cdninstagram.com/vp/cb8b2d6f4c92d272faff70b46438c23b/5C8F8A01/t51.2885-15/e15/21296885_512510259090836_7917735956357054464_n.jpg",
            "date": "2014-12-27T12:42:07.000Z",
            "tags": [],
            "likes": 458989,
            "url": "https://www.instagram.com/p/xHE0S1NqsT/",
            "comments": {
                "count": 25,
                "list": []
            },
            "mentions": []
        },
        {
            "caption": "I did this at 1am at night and I couldn't find golden heels so I am wearing slippers!!! Tag somebody and if you get tagged tag someone else!!! Let's try get this to 100k comments (colab with @ifunny.co)",
            "location": {
                "location_url": "",
                "location_name": "",
                "location_id": 0,
                "latitude": "",
                "longitude": ""
            },
            "img": "https://scontent-lga3-1.cdninstagram.com/vp/3ad1ab58b35c6debab950381917f28a3/5C9A37BC/t51.2885-15/e15/21435817_1271041816340346_7399621699114631168_n.jpg",
            "preview_img": "https://scontent-lga3-1.cdninstagram.com/vp/3ad1ab58b35c6debab950381917f28a3/5C9A37BC/t51.2885-15/e15/21435817_1271041816340346_7399621699114631168_n.jpg",
            "date": "2015-03-02T12:18:27.000Z",
            "tags": [],
            "likes": 373360,
            "url": "https://www.instagram.com/p/zuZx5Xtqmy/",
            "comments": {
                "count": 25,
                "list": []
            },
            "mentions": []
        },
        {
            "caption": "I don't know how your first tinder dates go but this is what happens with mine... I've been wanting to recreate this photo for a long time and after days and days of frantic tinder searching I found my Tyga \ud83d\ude0d This dude was down to take this photo in the middle of Hollywood Boulevard until security kicked us out of the area (I have no idea why as we weren't doing anything weird at all) Tinder changes lives \ud83d\ude1d #loveislove \ud83d\udc95#kyliejenner",
            "location": {
                "location_url": "https://www.instagram.com/explore/locations/1819644051625006/hollywood-boulevard/",
                "location_name": "Hollywood Boulevard",
                "location_id": "1819644051625006",
                "latitude": 34.10267,
                "longitude": -118.33923
            },
            "img": "https://scontent-lga3-1.cdninstagram.com/vp/d121f24e79202d0f105acbfd4a08df51/5CAAC062/t51.2885-15/e35/21433400_1712255305749469_611975858348883968_n.jpg",
            "preview_img": "https://scontent-lga3-1.cdninstagram.com/vp/c1fafcca5b6f78657b44d497a88c2263/5C9D2F87/t51.2885-15/sh0.08/e35/s640x640/21433400_1712255305749469_611975858348883968_n.jpg",
            "date": "2017-04-02T06:15:53.000Z",
            "tags": [
                "#loveislove",
                "#kyliejenner"
            ],
            "likes": 42244,
            "url": "https://www.instagram.com/p/BSX2BFfA33V/",
            "comments": {
                "count": 25,
                "list": []
            },
            "mentions": [
                "tyga",
                "kyliejenner",
                "waverider_",
                "amiryorke"
            ]
        },
        {
            "caption": "I had so much fun at the Grammys... But I can't believe Ri Ri stole ma look! I made my dress out of shredded pink paper \ud83d\ude02 seems it's Valentine's Day tag people you love and I will try spread the love and like your photos \u2764\ufe0f\ud83c\udf39",
            "location": {
                "location_url": "",
                "location_name": "",
                "location_id": 0,
                "latitude": "",
                "longitude": ""
            },
            "img": "https://scontent-lga3-1.cdninstagram.com/vp/2d28188f43e409cbc4e7e6a76379cede/5CA1842C/t51.2885-15/e15/21371855_1439267602821838_511177588706639872_n.jpg",
            "preview_img": "https://scontent-lga3-1.cdninstagram.com/vp/2d28188f43e409cbc4e7e6a76379cede/5CA1842C/t51.2885-15/e15/21371855_1439267602821838_511177588706639872_n.jpg",
            "date": "2015-02-13T13:08:06.000Z",
            "tags": [],
            "likes": 387598,
            "url": "https://www.instagram.com/p/zCt8rttqtg/",
            "comments": {
                "count": 25,
                "list": []
            },
            "mentions": []
        },
        {
            "caption": "HATERS BACK OFF... \ud83d\ude02\ud83d\ude02\ud83d\ude02 tag someone who needs to back off the booty!!",
            "location": {
                "location_url": "",
                "location_name": "",
                "location_id": 0,
                "latitude": "",
                "longitude": ""
            },
            "img": "https://scontent-lga3-1.cdninstagram.com/vp/dfa813af46f468ed8914ba88ecedb6a9/5CB157A5/t51.2885-15/e15/21372340_895589067248556_3860830704640196608_n.jpg",
            "preview_img": "https://scontent-lga3-1.cdninstagram.com/vp/dfa813af46f468ed8914ba88ecedb6a9/5CB157A5/t51.2885-15/e15/21372340_895589067248556_3860830704640196608_n.jpg",
            "date": "2015-04-09T13:19:09.000Z",
            "tags": [],
            "likes": 330074,
            "url": "https://www.instagram.com/p/1QW7q2tqkA/",
            "comments": {
                "count": 25,
                "list": []
            },
            "mentions": []
        },
        {
            "caption": "I wish I looked like @rubyrose tbh!! Tag a friend \ud83d\udc7d",
            "location": {
                "location_url": "",
                "location_name": "",
                "location_id": 0,
                "latitude": "",
                "longitude": ""
            },
            "img": "https://scontent-lga3-1.cdninstagram.com/vp/d88ee31d471d0c718c74381ba99b5583/5C8D4F2B/t51.2885-15/e35/21372937_113707062678370_8820534839275945984_n.jpg",
            "preview_img": "https://scontent-lga3-1.cdninstagram.com/vp/35e50eb9f0863350ad70fbb6d6153ee2/5C9C62CE/t51.2885-15/sh0.08/e35/s640x640/21372937_113707062678370_8820534839275945984_n.jpg",
            "date": "2015-07-19T05:59:59.000Z",
            "tags": [],
            "likes": 164618,
            "url": "https://www.instagram.com/p/5To9fSNqv1/",
            "comments": {
                "count": 25,
                "list": []
            },
            "mentions": []
        },
        {
            "caption": "Which is which?",
            "location": {
                "location_url": "",
                "location_name": "",
                "location_id": 0,
                "latitude": "",
                "longitude": ""
            },
            "img": "https://scontent-lga3-1.cdninstagram.com/vp/550bda0e8a4b40cb76d9b82cd554a289/5CB16A0A/t51.2885-15/e15/21433454_928502720622445_6526952123446329344_n.jpg",
            "preview_img": "https://scontent-lga3-1.cdninstagram.com/vp/550bda0e8a4b40cb76d9b82cd554a289/5CB16A0A/t51.2885-15/e15/21433454_928502720622445_6526952123446329344_n.jpg",
            "date": "2015-04-23T13:02:30.000Z",
            "tags": [],
            "likes": 274860,
            "url": "https://www.instagram.com/p/10YJ-8NqtJ/",
            "comments": {
                "count": 25,
                "list": []
            },
            "mentions": [
                "liamspersonal",
                "calvinklein",
                "justinbieber",
                "waverider_"
            ]
        },
        {
            "caption": "Collaboration with \"iFunny\" which you can download on the App Store! It was always my Teenage dream to lay in a cloud of cotton candy, see what I did there? Tag a friend who loves cotton candy \ud83d\ude0d",
            "location": {
                "location_url": "",
                "location_name": "",
                "location_id": 0,
                "latitude": "",
                "longitude": ""
            },
            "img": "https://scontent-lga3-1.cdninstagram.com/vp/8cfc1a2255e3319ce0a1aedda3f03e90/5CABB6D6/t51.2885-15/e15/21373600_130349787600657_1389225962373120000_n.jpg",
            "preview_img": "https://scontent-lga3-1.cdninstagram.com/vp/8cfc1a2255e3319ce0a1aedda3f03e90/5CABB6D6/t51.2885-15/e15/21373600_130349787600657_1389225962373120000_n.jpg",
            "date": "2015-01-31T12:43:40.000Z",
            "tags": [],
            "likes": 390904,
            "url": "https://www.instagram.com/p/yhM0XStqit/",
            "comments": {
                "count": 25,
                "list": []
            },
            "mentions": [
                "katyperry"
            ]
        },
        {
            "caption": "My goal is to look as good as @jlo when I am her age \ud83d\ude02",
            "location": {
                "location_url": "",
                "location_name": "",
                "location_id": 0,
                "latitude": "",
                "longitude": ""
            },
            "img": "https://scontent-lga3-1.cdninstagram.com/vp/99ef613b1c85b60b6c35a36aa48dccea/5C8B998C/t51.2885-15/e15/21435517_114576495917465_8846200902411878400_n.jpg",
            "preview_img": "https://scontent-lga3-1.cdninstagram.com/vp/99ef613b1c85b60b6c35a36aa48dccea/5C8B998C/t51.2885-15/e15/21435517_114576495917465_8846200902411878400_n.jpg",
            "date": "2014-12-04T13:34:37.000Z",
            "tags": [],
            "likes": 489570,
            "url": "https://www.instagram.com/p/wL8iwotqh0/",
            "comments": {
                "count": 25,
                "list": []
            },
            "mentions": []
        },
        {
            "caption": "HAPPY GRILLED CHEESE SANDWHICH DAY! go download \"skout\" and add me (Waveriderr) So I can chat with you guys, Send me a grilled cheese sandwhich gift and food gets donated over to the goats in Africa! I will also be donating some of my money over to help and encourage anyone to donate to a charity that they believe in!",
            "location": {
                "location_url": "",
                "location_name": "",
                "location_id": 0,
                "latitude": "",
                "longitude": ""
            },
            "img": "https://scontent-lga3-1.cdninstagram.com/vp/0e72d28b209f78f795877fd5eed618e3/5CA5325A/t51.2885-15/e15/21372280_2046590688910337_739964389121064960_n.jpg",
            "preview_img": "https://scontent-lga3-1.cdninstagram.com/vp/0e72d28b209f78f795877fd5eed618e3/5CA5325A/t51.2885-15/e15/21372280_2046590688910337_739964389121064960_n.jpg",
            "date": "2015-04-13T04:10:27.000Z",
            "tags": [],
            "likes": 302153,
            "url": "https://www.instagram.com/p/1ZrUYytqvB/",
            "comments": {
                "count": 25,
                "list": []
            },
            "mentions": []
        },
        {
            "caption": "Hello, it's me... It has being such a long time since I have being on Instagram and I have missed you guys so dearly. When I last left I was so unhealthy and unhappy with what was going on in my life. No Instagram caption can explain what I have been through and for that reason I have decided to write a book!!! A book which talks about struggling with mental health and dealing with abuse. The link is in my bio and I would love if you guys could read it and comment your thoughts in the bio, I'll follow people in the comments section \u2764\ufe0f",
            "location": {
                "location_url": "",
                "location_name": "",
                "location_id": 0,
                "latitude": "",
                "longitude": ""
            },
            "img": "https://scontent-lga3-1.cdninstagram.com/vp/77c67cb36bcab5b4422872d2d9995af7/5CA616C7/t51.2885-15/e35/21372182_512534589090694_8787657345661403136_n.jpg",
            "preview_img": "https://scontent-lga3-1.cdninstagram.com/vp/df74ff16a86e25116edcd4f779009ee2/5C8E4322/t51.2885-15/sh0.08/e35/s640x640/21372182_512534589090694_8787657345661403136_n.jpg",
            "date": "2016-03-16T04:41:01.000Z",
            "tags": [],
            "likes": 86018,
            "url": "https://www.instagram.com/p/BDADgAINqvD/",
            "comments": {
                "count": 25,
                "list": []
            },
            "mentions": [
                "waverider_",
                "adele"
            ]
        },
        {
            "caption": "One thing I've learnt after watching #13reasonswhy is how important it is for people to hold accountability and responsibility for the power of their words and how they can affect others! Always remember to consciously monitor what you say to somebody else because in all seriousness you never know how much your words can impact someone... Speak kind words, they travel \ud83d\ude07",
            "location": {
                "location_url": "",
                "location_name": "",
                "location_id": 0,
                "latitude": "",
                "longitude": ""
            },
            "img": "https://scontent-lga3-1.cdninstagram.com/vp/914afb543d6461a1ff0d3f3cab15d497/5C9074F1/t51.2885-15/e35/21372506_116493955754875_7003837417656418304_n.jpg",
            "preview_img": "https://scontent-lga3-1.cdninstagram.com/vp/c361856cca7bcca7e192dff68de194cc/5C776A14/t51.2885-15/sh0.08/e35/s640x640/21372506_116493955754875_7003837417656418304_n.jpg",
            "date": "2017-04-13T20:24:54.000Z",
            "tags": [
                "#13reasonswhy"
            ],
            "likes": 42919,
            "url": "https://www.instagram.com/p/BS1r7HdgmoP/",
            "comments": {
                "count": 25,
                "list": []
            },
            "mentions": [
                "waverider_",
                "selenagomez"
            ]
        },
        {
            "caption": "Guess who's back, back again. I have so much to share with you guys!!! Very shortly... Enjoy this photo of during Christmas \ud83d\ude02\u2764\ufe0f By the way it's my 19th birthday, I remember starting my Instagram journey with you guys when I was like... 15. Time has changed so much \ud83c\udf51\ud83c\udf51\ud83c\udf51 ily @kendalljenner",
            "location": {
                "location_url": "",
                "location_name": "",
                "location_id": 0,
                "latitude": "",
                "longitude": ""
            },
            "img": "https://scontent-lga3-1.cdninstagram.com/vp/8a4429d85fd5c80614e9d6caf1533a33/5C922BCF/t51.2885-15/e35/21296097_1962700853977264_1114651271530283008_n.jpg",
            "preview_img": "https://scontent-lga3-1.cdninstagram.com/vp/4b314d29c207c1f26986573393c14afd/5C93BE75/t51.2885-15/sh0.08/e35/s640x640/21296097_1962700853977264_1114651271530283008_n.jpg",
            "date": "2016-03-09T02:32:52.000Z",
            "tags": [],
            "likes": 78734,
            "url": "https://www.instagram.com/p/BCtzRUetqnJ/",
            "comments": {
                "count": 25,
                "list": []
            },
            "mentions": [
                "kendalljenner"
            ]
        },
        {
            "caption": "I've been drankin' watermelon \ud83d\udc45\ud83c\udf49... I thought it would be appropriate to designate my 'coming back' photo to Beyonc\u00e9 and her pregnancy shoot \ud83d\udc83\ud83c\udffd\ud83d\udc1d. It's been a long time- almost a year to be exact... Since I departed this little online community!\nIt's funny to think I grew up in front of so many of you - and so many of you grew up in front of me! I always held a sense of pride in the strong relationship I held with my audience, who always supported me through so much - I can't help but offer my deepest apologies for my long and often unexplained absences! From a social media influencer point of view I have held inconsistencies and unreliability to all of you, yet for some reason I always seem to come back to a flood of love and support \ud83d\udc95 I truly cannot express how much that means to me - I hope you all realise how much you all mean to me.\n\nIt truly is a privilege to have you all support me- and during my time offline I found a much deeper understanding & comprehension for the purpose of my influence. \u2728\n\nInfluence these days seems to be so easy to attain for superficial reasons (trust me I know, I used to put noodles on my head and balloons on my ass)...I find the true value of influence is the way it is used - for a purpose that is not selfish but selfless, with the intention to help others \ud83d\ude07\n\nI have learnt so much about myself, I have learnt to hold a strong level of contentment and respect for myself and the world around me. I have learnt the value of strong connections and how important it is to surround myself with positive people and to leave a loving impression on all those you encounter. Most importantly I have learnt the value of remaining a positive, uplifting presence in this world- to maintain pure intentions.\ud83c\udf0f I am throwing myself back into the chaotic beauty of this online platform that I started in my early teenage years! I can't promise much- I am to scared too. I don't want to let down or disappoint any of you who have remained so loyal and loving to me! I hope I am able to bring happiness and positivity to as many of you as possible, you always have meant so much to me\ud83d\udc95\n\nThank you for your patience! Keep persisting for positivity \ud83d\udc83",
            "location": {
                "location_url": "",
                "location_name": "",
                "location_id": 0,
                "latitude": "",
                "longitude": ""
            },
            "img": "https://scontent-lga3-1.cdninstagram.com/vp/68ce451d1c8a70fe80ee6a355ccc80a3/5CB17608/t51.2885-15/e35/21294867_1437697956318408_570773949315547136_n.jpg",
            "preview_img": "https://scontent-lga3-1.cdninstagram.com/vp/30f48467ab5804748427215e2b1dba60/5C99EBED/t51.2885-15/sh0.08/e35/s640x640/21294867_1437697956318408_570773949315547136_n.jpg",
            "date": "2017-02-22T07:00:28.000Z",
            "tags": [],
            "likes": 57165,
            "url": "https://www.instagram.com/p/BQzgHgmAtPU/",
            "comments": {
                "count": 25,
                "list": []
            },
            "mentions": [
                "waverider_",
                "beyonce"
            ]
        },
        {
            "caption": "Guess who's back, back again!!! So nice to see all your awesome faces. I have been gone for so long and I have missed you guys. I am going to do a follow spree!!! Repost with the caption \"follow me @waverider_\" and I'll follow your balloon booty \ud83c\udf51. ALSO IF YOU WOULD TAKE THE TIME TO READ THE FIRST CHAPTER OF MY BOOK IT WOULD MEAN THE ABSOLUTE WORLD TO ME (The link is in my bio, be sure to read the dedication and intro \u2764\ufe0f)",
            "location": {
                "location_url": "",
                "location_name": "",
                "location_id": 0,
                "latitude": "",
                "longitude": ""
            },
            "img": "https://scontent-lga3-1.cdninstagram.com/vp/94566ff697d619db0d988125fcb0ef5a/5CA0AD5B/t51.2885-15/e35/21294560_263423577497118_6463731957195866112_n.jpg",
            "preview_img": "https://scontent-lga3-1.cdninstagram.com/vp/94566ff697d619db0d988125fcb0ef5a/5CA0AD5B/t51.2885-15/e35/21294560_263423577497118_6463731957195866112_n.jpg",
            "date": "2016-03-16T20:50:51.000Z",
            "tags": [],
            "likes": 66916,
            "url": "https://www.instagram.com/p/BDByfWDNqpP/",
            "comments": {
                "count": 25,
                "list": []
            },
            "mentions": [
                "waverider_",
                "nickiminaj"
            ]
        },
        {
            "caption": "Hey guys!!! Want to see me dressing up as Demi Lovato? Watch the link in my bio, comment once you have watched it and I'll creep on your account \ud83d\ude18\ud83d\ude04 #demilovato",
            "location": {
                "location_url": "",
                "location_name": "",
                "location_id": 0,
                "latitude": "",
                "longitude": ""
            },
            "img": "https://scontent-lga3-1.cdninstagram.com/vp/ed8bda0e6a0b360d9f84d2d21e04dee1/5CAC2BC6/t51.2885-15/e35/21372456_145817809343598_447546591654445056_n.jpg",
            "preview_img": "https://scontent-lga3-1.cdninstagram.com/vp/4e1aa88c856bf82768276bad217f7314/5CAE05B5/t51.2885-15/sh0.08/e35/s640x640/21372456_145817809343598_447546591654445056_n.jpg",
            "date": "2015-07-11T13:17:17.000Z",
            "tags": [
                "#demilovato"
            ],
            "likes": 177480,
            "url": "https://www.instagram.com/p/4_0pbPtqgU/",
            "comments": {
                "count": 25,
                "list": []
            },
            "mentions": []
        },
        {
            "caption": "Hi guys sorry I am a little late on posting but what an amazing last 24 hours it has been \ud83c\udf89 my biological mother @arianagrande has turned 22 \ud83d\ude32\ud83d\ude1d and same-sex marriage is now legal across America \ud83d\udc69\u200d\u2764\ufe0f\u200d\ud83d\udc8b\u200d\ud83d\udc69\ud83d\udc68\u200d\u2764\ufe0f\u200d\ud83d\udc68\ud83c\udf08 I genuinely think this is so amazing and such a big step for society!!! #LoveWins \ud83d\ude4c\ud83c\udffc by the way... How cool would it be if you double tapped an Instagram photo and a rainbow heart came up?!?!",
            "location": {
                "location_url": "",
                "location_name": "",
                "location_id": 0,
                "latitude": "",
                "longitude": ""
            },
            "img": "https://scontent-lga3-1.cdninstagram.com/vp/e65262bfd5fdafb639a3ec4ec586fdac/5C99992B/t51.2885-15/e15/21433707_337248533406755_1216470025402056704_n.jpg",
            "preview_img": "https://scontent-lga3-1.cdninstagram.com/vp/e65262bfd5fdafb639a3ec4ec586fdac/5C99992B/t51.2885-15/e15/21433707_337248533406755_1216470025402056704_n.jpg",
            "date": "2015-06-27T21:24:04.000Z",
            "tags": [
                "#LoveWins"
            ],
            "likes": 230708,
            "url": "https://www.instagram.com/p/4cpOcHtqgc/",
            "comments": {
                "count": 25,
                "list": []
            },
            "mentions": []
        },
        {
            "caption": "Wishing everyone a day full of happiness and vibrancy!!! As much chaos and darkness that seems to be going on in the world right now just remember to keep your spirits high and strive to bring out the best in yourself and those around you \ud83c\udf1fI hope you all realise how grateful I am to be able to wake up everyday and have a flood of loving and uplifting comments from you all :) You guys mean so much to me and your support has gotten me through the years and you constantly inspire me to push myself as a creator and with my content!!! I have so much in the works for you all and I cannot wait to share it \ud83d\ude07 PEACE AND BLESSINGS TO YOU ALL XXX",
            "location": {
                "location_url": "",
                "location_name": "",
                "location_id": 0,
                "latitude": "",
                "longitude": ""
            },
            "img": "https://scontent-lga3-1.cdninstagram.com/vp/bb525051d4239fa2c6238e5b488bda73/5C988619/t51.2885-15/e35/21372553_1667036893368793_1201098998874636288_n.jpg",
            "preview_img": "https://scontent-lga3-1.cdninstagram.com/vp/9276ca3167b886fbbf006c11362bfede/5C9737A3/t51.2885-15/sh0.08/e35/s640x640/21372553_1667036893368793_1201098998874636288_n.jpg",
            "date": "2017-04-08T23:03:12.000Z",
            "tags": [],
            "likes": 37550,
            "url": "https://www.instagram.com/p/BSpGELEgcxp/",
            "comments": {
                "count": 25,
                "list": []
            },
            "mentions": [
                "waverider_",
                "littlebodybigheart"
            ]
        },
        {
            "caption": "Dressed up as the lovely @bethanynoelm always an honour dressing up as somebody so awesome \ud83d\udc4d I am going to be stalking some of your accounts so leave a comment!!!",
            "location": {
                "location_url": "",
                "location_name": "",
                "location_id": 0,
                "latitude": "",
                "longitude": ""
            },
            "img": "https://scontent-lga3-1.cdninstagram.com/vp/39331bd37df05ade79836bb964f23005/5C9902EC/t51.2885-15/e15/21372413_483752108646772_765743714839560192_n.jpg",
            "preview_img": "https://scontent-lga3-1.cdninstagram.com/vp/39331bd37df05ade79836bb964f23005/5C9902EC/t51.2885-15/e15/21372413_483752108646772_765743714839560192_n.jpg",
            "date": "2015-03-12T04:30:43.000Z",
            "tags": [],
            "likes": 361772,
            "url": "https://www.instagram.com/p/0HUMz_Nqrx/",
            "comments": {
                "count": 25,
                "list": []
            },
            "mentions": []
        },
        {
            "caption": "You can call me QUEEN Bey, but I ain't ever been royal... \ud83d\udc51\ud83e\udd27",
            "location": {
                "location_url": "",
                "location_name": "",
                "location_id": 0,
                "latitude": "",
                "longitude": ""
            },
            "img": "https://scontent-lga3-1.cdninstagram.com/vp/35b4f8b7e7c69c6e83dc31c5b8e8f8ba/5C8FAF63/t51.2885-15/e35/22637232_506646379692359_3526272045274890240_n.jpg",
            "preview_img": "https://scontent-lga3-1.cdninstagram.com/vp/1b9ce31a6ef62648bad55190abafbfb0/5CB25D86/t51.2885-15/sh0.08/e35/s640x640/22637232_506646379692359_3526272045274890240_n.jpg",
            "date": "2017-10-18T01:45:15.000Z",
            "tags": [],
            "likes": 27453,
            "url": "https://www.instagram.com/p/BaXxPG6gb9K/",
            "comments": {
                "count": 25,
                "list": []
            },
            "mentions": [
                "waverider_",
                "lordemusic"
            ]
        },
        {
            "caption": "I only had 6 dollars to make this photo... So I think I did ok \ud83d\ude02 tag your friends and I will try check out your page!!! Ily Ari",
            "location": {
                "location_url": "",
                "location_name": "",
                "location_id": 0,
                "latitude": "",
                "longitude": ""
            },
            "img": "https://scontent-lga3-1.cdninstagram.com/vp/fd624fec7b05b796be79f1f1a113e282/5CA70C01/t51.2885-15/e15/21296887_176008662963099_6670281929507471360_n.jpg",
            "preview_img": "https://scontent-lga3-1.cdninstagram.com/vp/fd624fec7b05b796be79f1f1a113e282/5CA70C01/t51.2885-15/e15/21296887_176008662963099_6670281929507471360_n.jpg",
            "date": "2015-01-19T12:44:41.000Z",
            "tags": [],
            "likes": 425863,
            "url": "https://www.instagram.com/p/yCTZTgtqgD/",
            "comments": {
                "count": 25,
                "list": []
            },
            "mentions": [
                "liamspersonal"
            ]
        },
        {
            "caption": "I apologise that it's been a while since I last posted! I recently turned 20 and have been enjoying the company of my friends in New York City!\ud83d\uddfdIt's crazy to think how much has changed since I first took my break from Instagram. So much has flourished within me and with experience comes growth!\nI feel as if we are in a time as vital as ever to project positivity and kindness to others! Through my 20 years of life I have always tried to encourage the value of embracing others for who they are and treating everyone with a mutual level of respect and authority. I can happily say I have developed confidence and a deeper understanding of my self worth and the potential I have to positively influence others. It almost feels selfish to hold a platform that can reach so many people and not use it for a sustainable and important purpose! Through my years of battling with mental health I find passion in dedicating myself to helping others see potential in themselves and their lives. Through anything you find yourself in please remind yourselves of the contribution you can offer to this community world! I can't believe the things I could of missed out on if I had made the decision to end my life. I could of missed out on so many beautiful connections with others and not ever have reached my full potential - Please remember you all hold unlimited potential. At around 15 when I first started this Instagram platform I could never have guessed the wave I was embarking on! It's definitely had its moments of uncertainty but I feel in the midst of tranquility with where I'm at in this current point in my life!!! I really hope that even if my photo can put a smile on a couple people's faces it is contributing towards a more friendly and contributing environment \ud83d\udc95 I have so many things I am excited to share with you all, and I cannot stress enough how much I appreciate your patience! I've always held such a respect for the people I have met on this community and watching the growth of people and their mindsets! It has been a pleasure to be able to contribute my own little spin on this community- I have missed you greatly \ud83d\udc84\ud83d\udc83\ud83c\udffd",
            "location": {
                "location_url": "",
                "location_name": "",
                "location_id": 0,
                "latitude": "",
                "longitude": ""
            },
            "img": "https://scontent-lga3-1.cdninstagram.com/vp/6b68d17910c6518f91d344b39f9e22a8/5CA39B85/t51.2885-15/e35/21433862_1434018543355786_9006145574709231616_n.jpg",
            "preview_img": "https://scontent-lga3-1.cdninstagram.com/vp/9dad529e05e19a4b422eb44f6f0b8c15/5C9FE8B0/t51.2885-15/sh0.08/e35/c41.0.998.998/s640x640/21433862_1434018543355786_9006145574709231616_n.jpg",
            "date": "2017-03-12T19:53:38.000Z",
            "tags": [],
            "likes": 37149,
            "url": "https://www.instagram.com/p/BRjO6JbAipp/",
            "comments": {
                "count": 25,
                "list": []
            },
            "mentions": [
                "arianagrande",
                "waverider_"
            ]
        },
        {
            "caption": "For those of you who don't know I dress up as amazing female celebrities, Caitlyn Jenner is no exception!!! She slays \ud83d\ude4c\ud83c\udffc\ud83d\ude4c\ud83c\udffc\ud83d\ude4c\ud83c\udffc in no way is this meant to be making fun of her :) I just wanted to show my support to Caitlyn and the LGBT community!!! Always be yourself \u2764\ufe0f\ud83d\udc9b\ud83d\udc9a\ud83d\udc99\ud83d\udc9c",
            "location": {
                "location_url": "",
                "location_name": "",
                "location_id": 0,
                "latitude": "",
                "longitude": ""
            },
            "img": "https://scontent-lga3-1.cdninstagram.com/vp/492a6ebdab987bf56feb03f0e2467c17/5CA1B9F9/t51.2885-15/e15/21296511_128159257818285_4198041983052152832_n.jpg",
            "preview_img": "https://scontent-lga3-1.cdninstagram.com/vp/492a6ebdab987bf56feb03f0e2467c17/5CA1B9F9/t51.2885-15/e15/21296511_128159257818285_4198041983052152832_n.jpg",
            "date": "2015-06-07T11:33:12.000Z",
            "tags": [],
            "likes": 259486,
            "url": "https://www.instagram.com/p/3oFtUnNqk-/",
            "comments": {
                "count": 25,
                "list": []
            },
            "mentions": []
        },
        {
            "caption": "My booty is literally poppin \ud83d\udc44 #thicc",
            "location": {
                "location_url": "",
                "location_name": "",
                "location_id": 0,
                "latitude": "",
                "longitude": ""
            },
            "img": "https://scontent-lga3-1.cdninstagram.com/vp/5659550bb95d8b7385c94515ef472de2/5CB1BECF/t51.2885-15/e35/21294435_125250148049998_223543744857636864_n.jpg",
            "preview_img": "https://scontent-lga3-1.cdninstagram.com/vp/3329faecde9f147bab1fad9bb70c93df/5C9033BC/t51.2885-15/sh0.08/e35/s640x640/21294435_125250148049998_223543744857636864_n.jpg",
            "date": "2017-05-22T09:37:59.000Z",
            "tags": [
                "#thicc"
            ],
            "likes": 34328,
            "url": "https://www.instagram.com/p/BUY85F4AH4K/",
            "comments": {
                "count": 25,
                "list": []
            },
            "mentions": [
                "kyliejenner",
                "waverider_"
            ]
        },
        {
            "caption": "I actually forgot which one I am \ud83d\ude02... I'm going to be liking people's photos so if you want me to like yours repost this photo and tag me in it and I will try my best to notice you \ud83d\ude04",
            "location": {
                "location_url": "",
                "location_name": "",
                "location_id": 0,
                "latitude": "",
                "longitude": ""
            },
            "img": "https://scontent-lga3-1.cdninstagram.com/vp/faaeb4fb8287f3f860fb7144e7572bb2/5C8FEA81/t51.2885-15/e15/21296926_710286505835263_7769273256355299328_n.jpg",
            "preview_img": "https://scontent-lga3-1.cdninstagram.com/vp/faaeb4fb8287f3f860fb7144e7572bb2/5C8FEA81/t51.2885-15/e15/21296926_710286505835263_7769273256355299328_n.jpg",
            "date": "2015-01-10T12:42:34.000Z",
            "tags": [],
            "likes": 452891,
            "url": "https://www.instagram.com/p/xrH_2QNqiZ/",
            "comments": {
                "count": 25,
                "list": []
            },
            "mentions": []
        }
    ]
}